[
  {
    "Date": "11 octobre 2023",
    "Titre": "4ever",
    "Saison": "Saison 1",
    "Plateforme": "Disney+"
  },
  {
    "Date": "12 octobre 2023",
    "Titre": "Berlin Bad Trip",
    "Saison": "Mini-série",
    "Plateforme": "Arte"
  },
  {
    "Date": "12 octobre 2023",
    "Titre": "Wreck : croisière sanglante",
    "Saison": "Saison 1",
    "Plateforme": "Syfy"
  },
  {
    "Date": "12 octobre 2023",
    "Titre": "Alphonse",
    "Saison": "Saison 1",
    "Plateforme": "Prime Video"
  },
  {
    "Date": "19 octobre 2023",
    "Titre": "Vise le coeur",
    "Saison": "Saison 2",
    "Plateforme": "TF1"
  },
  {
    "Date": "28 octobre 2023",
    "Titre": "The Control Room",
    "Saison": "Mini-série",
    "Plateforme": "Polar+"
  },
  {
    "Date": "30 octobre 2023",
    "Titre": "Candice Renoir",
    "Saison": "Inédit",
    "Plateforme": "France 2"
  },
  {
    "Date": "31 octobre 2023",
    "Titre": "Sophie Cross",
    "Saison": "Saison 2",
    "Plateforme": "France 3"
  },
  {
    "Date": "5 novembre 2023",
    "Titre": "Lawmen : l’histoire de Bass Reeves",
    "Saison": "Saison 1",
    "Plateforme": "Paramount+"
  },
  {
    "Date": "14 novembre 2023",
    "Titre": "Un Meurtre au bout du monde",
    "Saison": "Mini-série",
    "Plateforme": "Disney+"
  },
  {
    "Date": "16 novembre 2023",
    "Titre": "The Crown",
    "Saison": "Saison 6 partie 1",
    "Plateforme": "Netflix"
  },
  {
    "Date": "14 décembre 2023",
    "Titre": "The Crown",
    "Saison": "Saison 6 partie 2",
    "Plateforme": "Netflix"
  }
]