[
  {
    "Date": "20/11/2023",
    "Heure": "21:00:00",
    "Titre": "Pamela Rose, la série",
    "Saison": "Mini-série",
    "Plateforme": "Canal+",
    "Pays": "FRA",
    "Note": null
  },
  {
    "Date": "21/11/2023",
    "Heure": "00:00:00",
    "Titre": "Scooby-Doo : Mystères associés",
    "Saison": "Intégrale",
    "Plateforme": "Netflix",
    "Pays": "US",
    "Note": null
  },
  {
    "Date": "23/11/2023",
    "Heure": "00:00:00",
    "Titre": "Les Petits meurtres d’Agatha Christie",
    "Saison": "Saisons 1 et 2",
    "Plateforme": "Paramount+",
    "Pays": "FRA",
    "Note": null
  },
  {
    "Date": "23/11/2023",
    "Heure": "00:00:00",
    "Titre": "Fais pas ci, fais pas ça",
    "Saison": "Intégrale",
    "Plateforme": "Paramount+",
    "Pays": "FRA",
    "Note": null
  },
  {
    "Date": "23/11/2023",
    "Heure": "00:00:00",
    "Titre": "One Trillion Dollars",
    "Saison": "Saison 1",
    "Plateforme": "Paramount+",
    "Pays": "ALL, ITA",
    "Note": null
  },
  {
    "Date": "23/11/2023",
    "Heure": "20:55:00",
    "Titre": "Leverage: Redemption",
    "Saison": "Saison 2",
    "Plateforme": "Warner TV",
    "Pays": "US",
    "Note": null
  },
  {
    "Date": "24/11/2023",
    "Heure": "00:00:00",
    "Titre": "Split",
    "Saison": "Saison 1",
    "Plateforme": "France.tv Slash",
    "Pays": "FRA",
    "Note": null
  },
  {
    "Date": "24/11/2023",
    "Heure": "21:00:00",
    "Titre": "New York Police Judiciaire",
    "Saison": "Saison 22",
    "Plateforme": "13ème Rue",
    "Pays": "US",
    "Note": null
  },
  {
    "Date": "24/11/2023",
    "Heure": "00:00:00",
    "Titre": "Found",
    "Saison": "Saison 1",
    "Plateforme": "Pass Warner",
    "Pays": "US",
    "Note": null
  },
  {
    "Date": "24/11/2023",
    "Heure": "00:00:00",
    "Titre": "Une Famille presque normale",
    "Saison": "Mini-série",
    "Plateforme": "Netflix",
    "Pays": "SUE",
    "Note": null
  },
  {
    "Date": "25/11/2023",
    "Heure": "20:55:00",
    "Titre": "Témoin numéro 3",
    "Saison": "Mini-série",
    "Plateforme": "Polar+",
    "Pays": "UK",
    "Note": null
  },
  {
    "Date": "25/11/2023",
    "Heure": "00:00:00",
    "Titre": "Doctor Who",
    "Saison": "Specials",
    "Plateforme": "Disney+",
    "Pays": "UK",
    "Note": "Episode 2 le 02/12, Episode 3 le 09/12"
  },
  {
    "Date": "26/11/2023",
    "Heure": "21:10:00",
    "Titre": "Les Enquêtes de Vera",
    "Saison": "Saison 12",
    "Plateforme": "France 3",
    "Pays": "UK",
    "Note": null
  },
  {
    "Date": "26/11/2023",
    "Heure": "21:00:00",
    "Titre": "Follow",
    "Saison": "Saison 1",
    "Plateforme": "13ème Rue",
    "Pays": "FRA",
    "Note": null
  },
  {
    "Date": "28/11/2023",
    "Heure": "21:10:00",
    "Titre": "Bellefond",
    "Saison": "Inédit",
    "Plateforme": "France 3",
    "Pays": "FRA",
    "Note": null
  },
  {
    "Date": "28/11/2023",
    "Heure": "21:00:00",
    "Titre": "A Friend of The Family",
    "Saison": "Mini-série",
    "Plateforme": "OCS Max",
    "Pays": "US",
    "Note": null
  },
  {
    "Date": "29/11/2023",
    "Heure": "00:00:00",
    "Titre": "Culprits : Arnaque à l’anglaise",
    "Saison": "Saison 1",
    "Plateforme": "Disney+",
    "Pays": "UK",
    "Note": null
  },
  {
    "Date": "29/11/2023",
    "Heure": "00:00:00",
    "Titre": "Slow Horses",
    "Saison": "Saison 3",
    "Plateforme": "Apple TV+",
    "Pays": "UK",
    "Note": null
  },
  {
    "Date": "30/11/2023",
    "Heure": "21:10:00",
    "Titre": "Panda",
    "Saison": "Saison 1",
    "Plateforme": "TF1",
    "Pays": "FRA",
    "Note": null
  },
  {
    "Date": "30/11/2023",
    "Heure": "21:00:00",
    "Titre": "Love & Death",
    "Saison": "Mini-série",
    "Plateforme": "Canal+",
    "Pays": "US",
    "Note": null
  },
  {
    "Date": "30/11/2023",
    "Heure": "00:00:00",
    "Titre": "Virgin River",
    "Saison": "Saison 5 partie 2",
    "Plateforme": "Netflix",
    "Pays": "US",
    "Note": null
  },
  {
    "Date": "30/11/2023",
    "Heure": "00:00:00",
    "Titre": "Obliterated",
    "Saison": "Saison 1",
    "Plateforme": "Netflix",
    "Pays": "US",
    "Note": null
  },
  {
    "Date": "01/12/2023",
    "Heure": "00:00:00",
    "Titre": "Tout pour Agnès",
    "Saison": "Mini-série",
    "Plateforme": "Paramount+",
    "Pays": "FRA",
    "Note": null
  },
  {
    "Date": "01/12/2023",
    "Heure": "00:00:00",
    "Titre": "The Rookie",
    "Saison": "Saisons 1 à 3",
    "Plateforme": "Netflix",
    "Pays": "US",
    "Note": null
  },
  {
    "Date": "01/12/2023",
    "Heure": "00:00:00",
    "Titre": "Fisk",
    "Saison": "Saison 2",
    "Plateforme": "Netflix",
    "Pays": "AUS",
    "Note": null
  },
  {
    "Date": "01/12/2023",
    "Heure": "00:00:00",
    "Titre": "DC’s Legends of Tomorrow",
    "Saison": "Saison 7",
    "Plateforme": "Netflix",
    "Pays": "US",
    "Note": null
  },
  {
    "Date": "01/12/2023",
    "Heure": "00:00:00",
    "Titre": "Community",
    "Saison": "Saisons 1 à 6",
    "Plateforme": "Prime Video",
    "Pays": "US",
    "Note": null
  },
  {
    "Date": "01/12/2023",
    "Heure": "00:00:00",
    "Titre": "Sweet Home",
    "Saison": "Saison 2",
    "Plateforme": "Netflix",
    "Pays": "CDS",
    "Note": null
  },
  {
    "Date": "01/12/2023",
    "Heure": "00:00:00",
    "Titre": "Sept à la Maison",
    "Saison": "Intégrale",
    "Plateforme": "Prime Video",
    "Pays": "US",
    "Note": null
  },
  {
    "Date": "01/12/2023",
    "Heure": "00:00:00",
    "Titre": "Mes trois fils",
    "Saison": "Intégrale",
    "Plateforme": "Prime Video",
    "Pays": "US",
    "Note": null
  },
  {
    "Date": "01/12/2023",
    "Heure": "20:55:00",
    "Titre": "Les Enquêtes de Foyle",
    "Saison": "Saison 5",
    "Plateforme": "Polar+",
    "Pays": "UK",
    "Note": null
  },
  {
    "Date": "02/12/2023",
    "Heure": "00:00:00",
    "Titre": "Retour à Samdal-Ri",
    "Saison": "Saison 1",
    "Plateforme": "Netflix",
    "Pays": "CDS",
    "Note": null
  },
  {
    "Date": "02/12/2023",
    "Heure": "21:05:00",
    "Titre": "La Petite Histoire de France",
    "Saison": "Saison 5",
    "Plateforme": "W9",
    "Pays": "FRA",
    "Note": null
  },
  {
    "Date": "03/12/2023",
    "Heure": "00:00:00",
    "Titre": "Love Me",
    "Saison": "Saison 2",
    "Plateforme": "Paramount+",
    "Pays": "AUS",
    "Note": null
  },
  {
    "Date": "03/12/2023",
    "Heure": "00:00:00",
    "Titre": "Tale of The Nine Tailed",
    "Saison": "Saison 1",
    "Plateforme": "Netflix",
    "Pays": "CDS",
    "Note": null
  },
  {
    "Date": "03/12/2023",
    "Heure": "20:55:00",
    "Titre": "Reindeer Mafia",
    "Saison": "Saison 1",
    "Plateforme": "Polar+",
    "Pays": "FIN",
    "Note": null
  },
  {
    "Date": "04/12/2023",
    "Heure": "21:10:00",
    "Titre": "L’Art du crime",
    "Saison": "Inédit",
    "Plateforme": "France 2",
    "Pays": "FRA",
    "Note": null
  },
  {
    "Date": "05/12/2023",
    "Heure": "21:10:00",
    "Titre": "Alex Hugo",
    "Saison": "Inédit",
    "Plateforme": "France 3",
    "Pays": "FRA",
    "Note": null
  },
  {
    "Date": "06/12/2023",
    "Heure": "00:00:00",
    "Titre": "Soundtrack #2",
    "Saison": "Saison 1",
    "Plateforme": "Disney+",
    "Pays": "CDS",
    "Note": null
  },
  {
    "Date": "06/12/2023",
    "Heure": "00:00:00",
    "Titre": "Les Super-Vilains de Valley View",
    "Saison": "Saison 1",
    "Plateforme": "Disney+",
    "Pays": "US",
    "Note": null
  },
  {
    "Date": "06/12/2023",
    "Heure": "00:00:00",
    "Titre": "Wolf",
    "Saison": "Mini-série",
    "Plateforme": "Paramount+",
    "Pays": "UK",
    "Note": null
  },
  {
    "Date": "06/12/2023",
    "Heure": "00:00:00",
    "Titre": "Pax Massilia",
    "Saison": "Saison 1",
    "Plateforme": "Netflix",
    "Pays": "FRA",
    "Note": null
  },
  {
    "Date": "07/12/2023",
    "Heure": "00:00:00",
    "Titre": "Les Émissaires",
    "Saison": "Saison 1",
    "Plateforme": "Paramount+",
    "Pays": "ARG, MEX",
    "Note": null
  },
  {
    "Date": "07/12/2023",
    "Heure": "00:00:00",
    "Titre": "Knokke Off : jeunesse dorée",
    "Saison": "Saison 1",
    "Plateforme": "Netflix",
    "Pays": "BEL",
    "Note": null
  },
  {
    "Date": "07/12/2023",
    "Heure": "00:00:00",
    "Titre": "Analog Squad",
    "Saison": "Saison 1",
    "Plateforme": "Netflix",
    "Pays": "THA",
    "Note": null
  },
  {
    "Date": "07/12/2023",
    "Heure": "00:00:00",
    "Titre": "Je Déteste Noël",
    "Saison": "Saison 2",
    "Plateforme": "Netflix",
    "Pays": "ITA",
    "Note": null
  },
  {
    "Date": "07/12/2023",
    "Heure": "00:00:00",
    "Titre": "Ma vie avec les Walter Boys",
    "Saison": "Saison 1",
    "Plateforme": "Netflix",
    "Pays": "US",
    "Note": null
  },
  {
    "Date": "10/12/2023",
    "Heure": "00:00:00",
    "Titre": "Bupkis",
    "Saison": "Saison 1",
    "Plateforme": "Paramount+",
    "Pays": "US",
    "Note": null
  },
  {
    "Date": "10/12/2023",
    "Heure": "21:10:00",
    "Titre": "Les Mystères de L’Amour",
    "Saison": "Inédit",
    "Plateforme": "TMC",
    "Pays": "FRA",
    "Note": null
  },
  {
    "Date": "11/12/2023",
    "Heure": "00:00:00",
    "Titre": "True Beauty",
    "Saison": "Saison 1",
    "Plateforme": "Netflix",
    "Pays": "CDS",
    "Note": null
  },
  {
    "Date": "12/12/2023",
    "Heure": "00:00:00",
    "Titre": "The Ex-Wife",
    "Saison": "Saison 1",
    "Plateforme": "Paramount+",
    "Pays": "UK",
    "Note": null
  },
  {
    "Date": "12/12/2023",
    "Heure": "00:00:00",
    "Titre": "Los Farad",
    "Saison": "Saison 1",
    "Plateforme": "Prime Video",
    "Pays": "ESP",
    "Note": null
  },
  {
    "Date": "13/12/2023",
    "Heure": "00:00:00",
    "Titre": "The Influencer",
    "Saison": "Saison 1",
    "Plateforme": "Netflix",
    "Pays": "COL",
    "Note": null
  },
  {
    "Date": "13/12/2023",
    "Heure": "00:00:00",
    "Titre": 1670,
    "Saison": "Saison 1",
    "Plateforme": "Netflix",
    "Pays": "POL",
    "Note": null
  },
  {
    "Date": "13/12/2023",
    "Heure": "00:00:00",
    "Titre": "Undead Unluck",
    "Saison": "Saison 1",
    "Plateforme": "Disney+",
    "Pays": "JAP",
    "Note": null
  },
  {
    "Date": "13/12/2023",
    "Heure": "20:55:00",
    "Titre": "A la Maison Blanche",
    "Saison": "Saison 1",
    "Plateforme": "Warner TV",
    "Pays": "US",
    "Note": null
  },
  {
    "Date": "14/12/2023",
    "Heure": "00:00:00",
    "Titre": "Everything I Know About Love",
    "Saison": "Saison 1",
    "Plateforme": "Paramount+",
    "Pays": "UK",
    "Note": null
  },
  {
    "Date": "14/12/2023",
    "Heure": "00:00:00",
    "Titre": "Les Ailes de l’ambition",
    "Saison": "Saison 2",
    "Plateforme": "Netflix",
    "Pays": "TUR",
    "Note": null
  },
  {
    "Date": "14/12/2023",
    "Heure": "00:00:00",
    "Titre": "Yu Yu Hakusho",
    "Saison": "Saison 1",
    "Plateforme": "Netflix",
    "Pays": "JAP, US",
    "Note": null
  },
  {
    "Date": "14/12/2023",
    "Heure": "00:00:00",
    "Titre": "The Crown",
    "Saison": "Saison 6 partie 2",
    "Plateforme": "Netflix",
    "Pays": "UK",
    "Note": null
  },
  {
    "Date": "15/12/2023",
    "Heure": "00:00:00",
    "Titre": "Dream On",
    "Saison": "Intégrale",
    "Plateforme": "Paramount+",
    "Pays": "US",
    "Note": null
  },
  {
    "Date": "15/12/2023",
    "Heure": "00:00:00",
    "Titre": "Yoh! Christmas",
    "Saison": "Saison 1",
    "Plateforme": "Netflix",
    "Pays": "AFS",
    "Note": null
  },
  {
    "Date": "15/12/2023",
    "Heure": "00:00:00",
    "Titre": "The Shield",
    "Saison": "Intégrale",
    "Plateforme": "Prime Video",
    "Pays": "US",
    "Note": null
  },
  {
    "Date": "15/12/2023",
    "Heure": "00:00:00",
    "Titre": "Death’s Game",
    "Saison": "Saison 1",
    "Plateforme": "Prime Video",
    "Pays": "CDS",
    "Note": null
  },
  {
    "Date": "15/12/2023",
    "Heure": "00:00:00",
    "Titre": "Carol et la fin du monde",
    "Saison": "Saison 1",
    "Plateforme": "Netflix",
    "Pays": "US",
    "Note": null
  },
  {
    "Date": "15/12/2023",
    "Heure": "00:00:00",
    "Titre": "Grand Palais Chicha Lounge",
    "Saison": "Saison 1",
    "Plateforme": "France.tv Slash",
    "Pays": "FRA",
    "Note": null
  },
  {
    "Date": "15/12/2023",
    "Heure": "00:00:00",
    "Titre": "The Lovers",
    "Saison": "Saison 1",
    "Plateforme": "Paramount+",
    "Pays": "UK",
    "Note": null
  },
  {
    "Date": "15/12/2023",
    "Heure": "00:00:00",
    "Titre": "Reacher",
    "Saison": "Saison 2",
    "Plateforme": "Prime Video",
    "Pays": "US",
    "Note": null
  },
  {
    "Date": "17/12/2023",
    "Heure": "21:00:00",
    "Titre": "Agatha Christie : Les Enquêtes de Hjerson",
    "Saison": "Saison 1",
    "Plateforme": "Série Club",
    "Pays": "SUE",
    "Note": null
  },
  {
    "Date": "17/12/2023",
    "Heure": "21:00:00",
    "Titre": "The Killing Kind",
    "Saison": "Saison 1",
    "Plateforme": "OCS Pulp",
    "Pays": "UK",
    "Note": null
  },
  {
    "Date": "18/12/2023",
    "Heure": "20:55:00",
    "Titre": "Pagan Peak",
    "Saison": "Saison 3",
    "Plateforme": "Polar+",
    "Pays": "ALL, AUT",
    "Note": null
  },
  {
    "Date": "20/12/2023",
    "Heure": "00:00:00",
    "Titre": "Cindy la Regia",
    "Saison": "Saison 1",
    "Plateforme": "Netflix",
    "Pays": "MEX",
    "Note": null
  },
  {
    "Date": "20/12/2023",
    "Heure": "00:00:00",
    "Titre": "Dragons de Wonderhatch",
    "Saison": "Saison 1",
    "Plateforme": "Disney+",
    "Pays": "JAP",
    "Note": null
  },
  {
    "Date": "20/12/2023",
    "Heure": "00:00:00",
    "Titre": "Fargo",
    "Saison": "Saisons 1 à 4",
    "Plateforme": "MyCanal",
    "Pays": "US",
    "Note": null
  },
  {
    "Date": "20/12/2023",
    "Heure": "21:10:00",
    "Titre": "Harley Quinn",
    "Saison": "Saison 4",
    "Plateforme": "Warner TV Next",
    "Pays": "US",
    "Note": "Changement de date"
  },
  {
    "Date": "20/12/2023",
    "Heure": "00:00:00",
    "Titre": "Percy Jackson and the Olympians",
    "Saison": "Saison 1",
    "Plateforme": "Disney+",
    "Pays": "US",
    "Note": null
  },
  {
    "Date": "22/12/2023",
    "Heure": "00:00:00",
    "Titre": "La Créature de Kyŏngsŏng",
    "Saison": "Saison 1",
    "Plateforme": "Netflix",
    "Pays": "CDS",
    "Note": null
  },
  {
    "Date": "22/12/2023",
    "Heure": "00:00:00",
    "Titre": "Marvel’s What If… ?",
    "Saison": "Saison 2",
    "Plateforme": "Disney+",
    "Pays": "US",
    "Note": null
  },
  {
    "Date": "22/12/2023",
    "Heure": "00:00:00",
    "Titre": "Dickie",
    "Saison": "Saison 2",
    "Plateforme": "Adult Swim",
    "Pays": "BEL",
    "Note": null
  },
  {
    "Date": "23/12/2023",
    "Heure": "21:00:00",
    "Titre": "Starstruck",
    "Saison": "Saison 3",
    "Plateforme": "Canal+ Séries",
    "Pays": "UK",
    "Note": null
  },
  {
    "Date": "24/12/2023",
    "Heure": "00:00:00",
    "Titre": "Gabriel et ses petits démons",
    "Saison": "Saison 1",
    "Plateforme": "Netflix",
    "Pays": "MEX",
    "Note": null
  },
  {
    "Date": "25/12/2023",
    "Heure": "00:00:00",
    "Titre": "Yellowjackets",
    "Saison": "Saison 2",
    "Plateforme": "Paramount+",
    "Pays": "US",
    "Note": null
  },
  {
    "Date": "25/12/2023",
    "Heure": "00:00:00",
    "Titre": "Doctor Who : L’Église de Ruby Road",
    "Saison": "Inédit",
    "Plateforme": "Disney+",
    "Pays": "UK",
    "Note": null
  },
  {
    "Date": "26/12/2023",
    "Heure": "21:00:00",
    "Titre": "Orphan Black : Echoes",
    "Saison": "Saison 1",
    "Plateforme": "OCS Max",
    "Pays": "CAN",
    "Note": null
  },
  {
    "Date": "28/12/2023",
    "Heure": "00:00:00",
    "Titre": "La Réceptionniste Pokemon",
    "Saison": "Saison 1",
    "Plateforme": "Netflix",
    "Pays": "JAP",
    "Note": null
  },
  {
    "Date": "28/12/2023",
    "Heure": "21:00:00",
    "Titre": "Blue Bloods",
    "Saison": "Saison 13",
    "Plateforme": "Série Club",
    "Pays": "US",
    "Note": null
  },
  {
    "Date": "29/12/2023",
    "Heure": "00:00:00",
    "Titre": "Insecure",
    "Saison": "Intégrale",
    "Plateforme": "Prime Video",
    "Pays": "US",
    "Note": null
  },
  {
    "Date": "29/12/2023",
    "Heure": "00:00:00",
    "Titre": "Berlín",
    "Saison": "Saison 1",
    "Plateforme": "Netflix",
    "Pays": "ESP",
    "Note": null
  },
  {
    "Date": "30/12/2023",
    "Heure": "00:00:00",
    "Titre": "Sister, Sister",
    "Saison": "Saisons 1 à 6",
    "Plateforme": "Prime Video",
    "Pays": "US",
    "Note": null
  },
  {
    "Date": "30/12/2023",
    "Heure": "00:00:00",
    "Titre": "Moesha",
    "Saison": "Saisons 1 à 6",
    "Plateforme": "Prime Video",
    "Pays": "US",
    "Note": null
  },
  {
    "Date": "30/12/2023",
    "Heure": "00:00:00",
    "Titre": "The Affair",
    "Saison": "Intégrale",
    "Plateforme": "Prime Video",
    "Pays": "US",
    "Note": null
  },
  {
    "Date": "04/01/2024",
    "Heure": "20:55:00",
    "Titre": "Riverdale",
    "Saison": "Saison 6",
    "Plateforme": "Warner TV",
    "Pays": "US",
    "Note": null
  },
  {
    "Date": "07/01/2024",
    "Heure": "21:00:00",
    "Titre": "The Lazarus Project",
    "Saison": "Saison 2",
    "Plateforme": "OCS Pulp",
    "Pays": "UK",
    "Note": null
  },
  {
    "Date": "08/01/2024",
    "Heure": "14:00:00",
    "Titre": "Plus belle la vie, encore plus belle",
    "Saison": "Feuilleton quotidien",
    "Plateforme": "TF1",
    "Pays": "FRA",
    "Note": "Horaire à confirmer"
  },
  {
    "Date": "10/01/2024",
    "Heure": "00:00:00",
    "Titre": "Echo",
    "Saison": "Saison 1",
    "Plateforme": "Disney+",
    "Pays": "US",
    "Note": null
  },
  {
    "Date": "12/01/2024",
    "Heure": "00:00:00",
    "Titre": "Criminal Record",
    "Saison": "Saison 1",
    "Plateforme": "Apple TV+",
    "Pays": "UK",
    "Note": null
  },
  {
    "Date": "15/01/2024",
    "Heure": "00:00:00",
    "Titre": "True Detective",
    "Saison": "Saison 4",
    "Plateforme": "Pass Warner",
    "Pays": "US",
    "Note": "Titre complet de la saison 4 = “True Detective: Night Country”"
  },
  {
    "Date": "17/01/2024",
    "Heure": "00:00:00",
    "Titre": "Le Renard : Prince des voleurs",
    "Saison": "Saison 1",
    "Plateforme": "Disney+",
    "Pays": "AUS",
    "Note": "Titre original : The Artful Dodger"
  },
  {
    "Date": "19/01/2024",
    "Heure": "00:00:00",
    "Titre": "Hazbin Hotel",
    "Saison": "Saison 1",
    "Plateforme": "Prime Video",
    "Pays": "US",
    "Note": null
  },
  {
    "Date": "19/01/2024",
    "Heure": "00:00:00",
    "Titre": "Cristobal Balenciaga",
    "Saison": "Saison 1",
    "Plateforme": "Disney+",
    "Pays": "ESP",
    "Note": null
  },
  {
    "Date": "22/01/2024",
    "Heure": "00:00:00",
    "Titre": "Dickie",
    "Saison": "Saison 2 partie 2",
    "Plateforme": "Adult Swim",
    "Pays": "BEL",
    "Note": null
  },
  {
    "Date": "23/01/2024",
    "Heure": "20:55:00",
    "Titre": "Spencer Sisters : Detectives Agency",
    "Saison": "Saison 1",
    "Plateforme": "Warner TV",
    "Pays": "CAN",
    "Note": null
  },
  {
    "Date": "25/01/2024",
    "Heure": "00:00:00",
    "Titre": "Masters of The Universe: Revolution",
    "Saison": "Saison 1",
    "Plateforme": "Netflix",
    "Pays": "US",
    "Note": null
  },
  {
    "Date": "25/01/2024",
    "Heure": "00:00:00",
    "Titre": "Griselda",
    "Saison": "Mini-série",
    "Plateforme": "Netflix",
    "Pays": "US",
    "Note": null
  },
  {
    "Date": "26/01/2024",
    "Heure": "00:00:00",
    "Titre": "Masters of The Air",
    "Saison": "Mini-série",
    "Plateforme": "Apple TV+",
    "Pays": "US",
    "Note": null
  },
  {
    "Date": "26/01/2024",
    "Heure": "00:00:00",
    "Titre": "Expats",
    "Saison": "Mini-série",
    "Plateforme": "Prime Video",
    "Pays": "US",
    "Note": null
  },
  {
    "Date": "02/02/2024",
    "Heure": "00:00:00",
    "Titre": "Mr. & Mrs. Smith",
    "Saison": "Saison 1",
    "Plateforme": "Prime Video",
    "Pays": "US",
    "Note": null
  },
  {
    "Date": "08/02/2024",
    "Heure": "00:00:00",
    "Titre": "One Day",
    "Saison": "Mini-série",
    "Plateforme": "Netflix",
    "Pays": "UK",
    "Note": null
  },
  {
    "Date": "14/02/2024",
    "Heure": "00:00:00",
    "Titre": "The New Look",
    "Saison": "Mini-série",
    "Plateforme": "Apple TV+",
    "Pays": "US",
    "Note": null
  },
  {
    "Date": "22/02/2024",
    "Heure": "00:00:00",
    "Titre": "Avatar, le dernier maître de l’air",
    "Saison": "Saison 1",
    "Plateforme": "Netflix",
    "Pays": "US",
    "Note": null
  },
  {
    "Date": "21/03/2024",
    "Heure": "00:00:00",
    "Titre": "Le Problème à 3 corps",
    "Saison": "Saison 1",
    "Plateforme": "Netflix",
    "Pays": "US",
    "Note": "Titre original : “3 Body Problem”"
  },
  {
    "Date": "12/04/2024",
    "Heure": "00:00:00",
    "Titre": "Fallout",
    "Saison": "Saison 1",
    "Plateforme": "Prime Video",
    "Pays": "US",
    "Note": null
  }
]
