[
  {
    "Date": "18/12/2023",
    "Heure": "20:55:00",
    "Titre": "Pagan Peak",
    "Saison": "Saison 3",
    "Plateforme": "Polar+",
    "Pays": "ALL, AUT",
    "Note": null
  },
  {
    "Date": "20/12/2023",
    "Heure": "00:00:00",
    "Titre": "Cindy la Regia",
    "Saison": "Saison 1",
    "Plateforme": "Netflix",
    "Pays": "MEX",
    "Note": null
  },
  {
    "Date": "20/12/2023",
    "Heure": "00:00:00",
    "Titre": "Dragons de Wonderhatch",
    "Saison": "Saison 1",
    "Plateforme": "Disney+",
    "Pays": "JAP",
    "Note": null
  },
  {
    "Date": "20/12/2023",
    "Heure": "00:00:00",
    "Titre": "Fargo",
    "Saison": "Saisons 1 à 4",
    "Plateforme": "MyCanal",
    "Pays": "US",
    "Note": null
  },
  {
    "Date": "20/12/2023",
    "Heure": "21:10:00",
    "Titre": "Harley Quinn",
    "Saison": "Saison 4",
    "Plateforme": "Warner TV Next",
    "Pays": "US",
    "Note": "Changement de date"
  },
  {
    "Date": "20/12/2023",
    "Heure": "00:00:00",
    "Titre": "Percy Jackson and the Olympians",
    "Saison": "Saison 1",
    "Plateforme": "Disney+",
    "Pays": "US",
    "Note": null
  },
  {
    "Date": "22/12/2023",
    "Heure": "00:00:00",
    "Titre": "La Créature de Kyŏngsŏng",
    "Saison": "Saison 1",
    "Plateforme": "Netflix",
    "Pays": "CDS",
    "Note": null
  },
  {
    "Date": "22/12/2023",
    "Heure": "00:00:00",
    "Titre": "Marvel’s What If… ?",
    "Saison": "Saison 2",
    "Plateforme": "Disney+",
    "Pays": "US",
    "Note": null
  },
  {
    "Date": "22/12/2023",
    "Heure": "00:00:00",
    "Titre": "Dickie",
    "Saison": "Saison 2",
    "Plateforme": "Adult Swim",
    "Pays": "BEL",
    "Note": null
  },
  {
    "Date": "23/12/2023",
    "Heure": "21:00:00",
    "Titre": "Starstruck",
    "Saison": "Saison 3",
    "Plateforme": "Canal+ Séries",
    "Pays": "UK",
    "Note": null
  },
  {
    "Date": "24/12/2023",
    "Heure": "00:00:00",
    "Titre": "Gabriel et ses petits démons",
    "Saison": "Saison 1",
    "Plateforme": "Netflix",
    "Pays": "MEX",
    "Note": null
  },
  {
    "Date": "25/12/2023",
    "Heure": "00:00:00",
    "Titre": "Yellowjackets",
    "Saison": "Saison 2",
    "Plateforme": "Paramount+",
    "Pays": "US",
    "Note": null
  },
  {
    "Date": "25/12/2023",
    "Heure": "00:00:00",
    "Titre": "Doctor Who : L’Église de Ruby Road",
    "Saison": "Inédit",
    "Plateforme": "Disney+",
    "Pays": "UK",
    "Note": null
  },
  {
    "Date": "26/12/2023",
    "Heure": "21:00:00",
    "Titre": "Orphan Black : Echoes",
    "Saison": "Saison 1",
    "Plateforme": "OCS Max",
    "Pays": "CAN",
    "Note": null
  },
  {
    "Date": "27/12/2023",
    "Heure": "00:00:00",
    "Titre": "Meurtres au paradis",
    "Saison": "Spécial Noël",
    "Plateforme": "France 2",
    "Pays": "FRA, UK",
    "Note": null
  },
  {
    "Date": "28/12/2023",
    "Heure": "20:55:00",
    "Titre": "Icon of French Cinema",
    "Saison": "Mini-série",
    "Plateforme": "Arte",
    "Pays": "FRA",
    "Note": null
  },
  {
    "Date": "28/12/2023",
    "Heure": "00:00:00",
    "Titre": "La Réceptionniste Pokemon",
    "Saison": "Saison 1",
    "Plateforme": "Netflix",
    "Pays": "JAP",
    "Note": null
  },
  {
    "Date": "28/12/2023",
    "Heure": "21:00:00",
    "Titre": "Blue Bloods",
    "Saison": "Saison 13",
    "Plateforme": "Série Club",
    "Pays": "US",
    "Note": null
  },
  {
    "Date": "29/12/2023",
    "Heure": "00:00:00",
    "Titre": "Insecure",
    "Saison": "Intégrale",
    "Plateforme": "Prime Video",
    "Pays": "US",
    "Note": null
  },
  {
    "Date": "29/12/2023",
    "Heure": "00:00:00",
    "Titre": "Berlín",
    "Saison": "Saison 1",
    "Plateforme": "Netflix",
    "Pays": "ESP",
    "Note": null
  },
  {
    "Date": "30/12/2023",
    "Heure": "21:00:00",
    "Titre": "Threesome",
    "Saison": "Saison 2",
    "Plateforme": "Canal+ Séries",
    "Pays": "SUE",
    "Note": "Diffusion en marathon"
  },
  {
    "Date": "30/12/2023",
    "Heure": "00:00:00",
    "Titre": "Sister, Sister",
    "Saison": "Saisons 1 à 6",
    "Plateforme": "Prime Video",
    "Pays": "US",
    "Note": null
  },
  {
    "Date": "30/12/2023",
    "Heure": "00:00:00",
    "Titre": "Moesha",
    "Saison": "Saisons 1 à 6",
    "Plateforme": "Prime Video",
    "Pays": "US",
    "Note": null
  },
  {
    "Date": "30/12/2023",
    "Heure": "00:00:00",
    "Titre": "The Affair",
    "Saison": "Intégrale",
    "Plateforme": "Prime Video",
    "Pays": "US",
    "Note": null
  },
  {
    "Date": "01/01/2024",
    "Heure": "00:00:00",
    "Titre": "Neumatt",
    "Saison": "Saison 2",
    "Plateforme": "Netflix",
    "Pays": "SUI",
    "Note": null
  },
  {
    "Date": "01/01/2024",
    "Heure": "00:00:00",
    "Titre": "Parents mode d’emploi",
    "Saison": "Intégrale",
    "Plateforme": "Netflix",
    "Pays": "FRA",
    "Note": null
  },
  {
    "Date": "01/01/2024",
    "Heure": "00:00:00",
    "Titre": "Power Players",
    "Saison": "Saison 2",
    "Plateforme": "Netflix",
    "Pays": "US",
    "Note": null
  },
  {
    "Date": "01/01/2024",
    "Heure": "00:00:00",
    "Titre": "Orange Days",
    "Saison": "Intégrale",
    "Plateforme": "Netflix",
    "Pays": "JAP",
    "Note": null
  },
  {
    "Date": "01/01/2024",
    "Heure": "00:00:00",
    "Titre": "Double piège",
    "Saison": "Mini-série",
    "Plateforme": "Netflix",
    "Pays": "UK",
    "Note": "Titre original : Fool Me Once"
  },
  {
    "Date": "02/01/2024",
    "Heure": "21:10:00",
    "Titre": "Tandem",
    "Saison": "Inédit",
    "Plateforme": "France 3",
    "Pays": "FRA",
    "Note": null
  },
  {
    "Date": "02/01/2024",
    "Heure": "20:55:00",
    "Titre": "Dark Winds",
    "Saison": "Saison 1",
    "Plateforme": "Polar+",
    "Pays": "US",
    "Note": null
  },
  {
    "Date": "03/01/2024",
    "Heure": "00:00:00",
    "Titre": "Ishura",
    "Saison": "Saison 1",
    "Plateforme": "Disney+",
    "Pays": "JAP",
    "Note": null
  },
  {
    "Date": "03/01/2024",
    "Heure": "00:00:00",
    "Titre": "FBI Promotion 2009",
    "Saison": "Mini-série",
    "Plateforme": "Disney+",
    "Pays": "US",
    "Note": "Titre original : Class of ‘09"
  },
  {
    "Date": "04/01/2024",
    "Heure": "00:00:00",
    "Titre": "Gloutons et dragons",
    "Saison": "Saison 1",
    "Plateforme": "Netflix",
    "Pays": "JAP",
    "Note": null
  },
  {
    "Date": "04/01/2024",
    "Heure": "21:00:00",
    "Titre": "Almost Paradise",
    "Saison": "Saison 2",
    "Plateforme": "13ème Rue",
    "Pays": "US",
    "Note": null
  },
  {
    "Date": "04/01/2024",
    "Heure": "20:55:00",
    "Titre": "La Saison du Verseau",
    "Saison": "Mini-série",
    "Plateforme": "Arte",
    "Pays": "ALL, BEL",
    "Note": null
  },
  {
    "Date": "04/01/2024",
    "Heure": "00:00:00",
    "Titre": "Les Frères Sun",
    "Saison": "Saison 1",
    "Plateforme": "Netflix",
    "Pays": "US",
    "Note": null
  },
  {
    "Date": "04/01/2024",
    "Heure": "20:55:00",
    "Titre": "Riverdale",
    "Saison": "Saison 6",
    "Plateforme": "Warner TV",
    "Pays": "US",
    "Note": null
  },
  {
    "Date": "05/01/2024",
    "Heure": "00:00:00",
    "Titre": "La Créature de Kyŏngsŏng",
    "Saison": "Partie 2",
    "Plateforme": "Netflix",
    "Pays": "CDS",
    "Note": null
  },
  {
    "Date": "05/01/2024",
    "Heure": "21:10:00",
    "Titre": "César Wagner",
    "Saison": "inédit",
    "Plateforme": "France 2",
    "Pays": "FRA",
    "Note": null
  },
  {
    "Date": "06/01/2024",
    "Heure": "21:10:00",
    "Titre": "The Rookie",
    "Saison": "Saison 4",
    "Plateforme": "M6",
    "Pays": "US",
    "Note": "Déjà diffusée sur Série Club"
  },
  {
    "Date": "07/01/2024",
    "Heure": "00:45:00",
    "Titre": "81ème Golden Globes",
    "Saison": "Cérémonie",
    "Plateforme": "Canal+",
    "Pays": "US",
    "Note": "Diffusion dans la nuit du dimanche 7 au lundi 8"
  },
  {
    "Date": "07/01/2024",
    "Heure": "21:10:00",
    "Titre": "Meurtres en eaux troubles",
    "Saison": "Inédit",
    "Plateforme": "France 3",
    "Pays": "ALL, AUT",
    "Note": null
  },
  {
    "Date": "07/01/2024",
    "Heure": "21:00:00",
    "Titre": "Arcadia",
    "Saison": "Saison 1",
    "Plateforme": "Syfy",
    "Pays": "BEL, PB",
    "Note": null
  },
  {
    "Date": "07/01/2024",
    "Heure": "21:00:00",
    "Titre": "Alert",
    "Saison": "Saison 1",
    "Plateforme": "Teva",
    "Pays": "US",
    "Note": "Titre original : “Alert: Missing Persons Unit”"
  },
  {
    "Date": "07/01/2024",
    "Heure": "21:00:00",
    "Titre": "The Lazarus Project",
    "Saison": "Saison 2",
    "Plateforme": "OCS Pulp",
    "Pays": "UK",
    "Note": null
  },
  {
    "Date": "08/01/2024",
    "Heure": "00:00:00",
    "Titre": "Synduality Noir",
    "Saison": "Partie 2",
    "Plateforme": "Disney+",
    "Pays": "JAP",
    "Note": null
  },
  {
    "Date": "08/01/2024",
    "Heure": "21:10:00",
    "Titre": "Tout pour Agnès",
    "Saison": "Mini-série",
    "Plateforme": "France 2",
    "Pays": "FRA",
    "Note": "Déjà disponible sur Paramount+"
  },
  {
    "Date": "08/01/2024",
    "Heure": "21:10:00",
    "Titre": "Sam",
    "Saison": "Saison 7",
    "Plateforme": "TF1",
    "Pays": "FRA",
    "Note": null
  },
  {
    "Date": "08/01/2024",
    "Heure": "21:00:00",
    "Titre": "Without Sin",
    "Saison": "Mini-série",
    "Plateforme": "Canal+",
    "Pays": "UK",
    "Note": null
  },
  {
    "Date": "08/01/2024",
    "Heure": "13:40:00",
    "Titre": "Plus belle la vie, encore plus belle",
    "Saison": "Feuilleton quotidien",
    "Plateforme": "TF1",
    "Pays": "FRA",
    "Note": null
  },
  {
    "Date": "09/01/2024",
    "Heure": "00:00:00",
    "Titre": "Ag3nda",
    "Saison": "Saison 3",
    "Plateforme": "Netflix",
    "Pays": "ITA",
    "Note": null
  },
  {
    "Date": "09/01/2024",
    "Heure": "23:20:00",
    "Titre": "Sissi",
    "Saison": "Saison 3",
    "Plateforme": "W9",
    "Pays": "ALL, AUT",
    "Note": null
  },
  {
    "Date": "09/01/2024",
    "Heure": "21:10:00",
    "Titre": "SWAT",
    "Saison": "Reprise saison 6",
    "Plateforme": "TF1",
    "Pays": "US",
    "Note": "Reprise avec l’épisode 6.11"
  },
  {
    "Date": "09/01/2024",
    "Heure": "21:00:00",
    "Titre": "SurrealEstate",
    "Saison": "Saison 2",
    "Plateforme": "Syfy",
    "Pays": "CAN, US",
    "Note": null
  },
  {
    "Date": "10/01/2024",
    "Heure": "00:00:00",
    "Titre": "American Horror Stories",
    "Saison": "Saison 3 partie 1",
    "Plateforme": "Disney+",
    "Pays": "US",
    "Note": null
  },
  {
    "Date": "10/01/2024",
    "Heure": "21:10:00",
    "Titre": "Marianne",
    "Saison": "Saison 2",
    "Plateforme": "France 2",
    "Pays": "FRA",
    "Note": null
  },
  {
    "Date": "10/01/2024",
    "Heure": "21:10:00",
    "Titre": "Esprits Criminels : Evolution",
    "Saison": "Saison 1",
    "Plateforme": "TF1",
    "Pays": "US",
    "Note": "Revival de la série Esprits Criminels sous le titre VO “Criminal Minds : Evolution”"
  },
  {
    "Date": "10/01/2024",
    "Heure": "00:00:00",
    "Titre": "Echo",
    "Saison": "Saison 1",
    "Plateforme": "Disney+",
    "Pays": "US",
    "Note": null
  },
  {
    "Date": "11/01/2024",
    "Heure": "00:00:00",
    "Titre": "Detective Forst",
    "Saison": "Saison 1",
    "Plateforme": "Netflix",
    "Pays": "POL",
    "Note": null
  },
  {
    "Date": "11/01/2024",
    "Heure": "00:00:00",
    "Titre": "Champion",
    "Saison": "Saison 1",
    "Plateforme": "Netflix",
    "Pays": "UK",
    "Note": null
  },
  {
    "Date": "11/01/2024",
    "Heure": "00:00:00",
    "Titre": "Sonic Prime",
    "Saison": "Saison 3",
    "Plateforme": "Netflix",
    "Pays": "US",
    "Note": null
  },
  {
    "Date": "11/01/2024",
    "Heure": "00:00:00",
    "Titre": "Le Garçon et l’Univers",
    "Saison": "Mini-série",
    "Plateforme": "Netflix",
    "Pays": "AUS",
    "Note": "Titre original : Boy Swallows Universe"
  },
  {
    "Date": "11/01/2024",
    "Heure": "20:55:00",
    "Titre": "Mystery Road : les origines",
    "Saison": "Saison 1",
    "Plateforme": "Arte",
    "Pays": "AUS",
    "Note": null
  },
  {
    "Date": "11/01/2024",
    "Heure": "21:10:00",
    "Titre": "Rivière-perdue",
    "Saison": "Mini-série",
    "Plateforme": "TF1",
    "Pays": "FRA",
    "Note": null
  },
  {
    "Date": "12/01/2024",
    "Heure": "00:00:00",
    "Titre": "Based on a True Story",
    "Saison": "Saison 1",
    "Plateforme": "Paramount+",
    "Pays": "US",
    "Note": null
  },
  {
    "Date": "12/01/2024",
    "Heure": "00:00:00",
    "Titre": "SkyMed",
    "Saison": "Saison 2",
    "Plateforme": "Paramount+",
    "Pays": "CAN",
    "Note": "Date à confirmer"
  },
  {
    "Date": "12/01/2024",
    "Heure": "00:00:00",
    "Titre": "Criminal Record",
    "Saison": "Saison 1",
    "Plateforme": "Apple TV+",
    "Pays": "UK",
    "Note": null
  },
  {
    "Date": "15/01/2024",
    "Heure": "20:55:00",
    "Titre": "Rapa",
    "Saison": "Saison 2",
    "Plateforme": "Polar+",
    "Pays": "ESP",
    "Note": null
  },
  {
    "Date": "15/01/2024",
    "Heure": "23:30:00",
    "Titre": "La nuit des Emmys",
    "Saison": "Cérémonie",
    "Plateforme": "Canal+",
    "Pays": "US",
    "Note": "Diffusion du reportage En Route pour les Emmys + Tapis Rouge + Cérémonie des Emmy Awards dans la nuit du lundi 15 au mardi 16"
  },
  {
    "Date": "15/01/2024",
    "Heure": "00:00:00",
    "Titre": "True Detective",
    "Saison": "Saison 4",
    "Plateforme": "Pass Warner",
    "Pays": "US",
    "Note": "Titre complet de la saison 4 = “True Detective: Night Country”"
  },
  {
    "Date": "17/01/2024",
    "Heure": "00:00:00",
    "Titre": "End of The Line",
    "Saison": "Saison 1",
    "Plateforme": "Netflix",
    "Pays": "BRE",
    "Note": null
  },
  {
    "Date": "17/01/2024",
    "Heure": "00:00:00",
    "Titre": "A Shop For Killers",
    "Saison": "Saison 1",
    "Plateforme": "Disney+",
    "Pays": "CDS",
    "Note": null
  },
  {
    "Date": "17/01/2024",
    "Heure": "00:00:00",
    "Titre": "Le Renard : Prince des voleurs",
    "Saison": "Saison 1",
    "Plateforme": "Disney+",
    "Pays": "AUS",
    "Note": "Titre original : The Artful Dodger"
  },
  {
    "Date": "18/01/2024",
    "Heure": "00:00:00",
    "Titre": "NCIS: Sydney",
    "Saison": "Saison 1",
    "Plateforme": "Paramount+",
    "Pays": "US",
    "Note": null
  },
  {
    "Date": "18/01/2024",
    "Heure": "00:00:00",
    "Titre": "Kübra",
    "Saison": "Saison 1",
    "Plateforme": "Netflix",
    "Pays": "TUR",
    "Note": null
  },
  {
    "Date": "18/01/2024",
    "Heure": "22:50:00",
    "Titre": "Fellow Travelers",
    "Saison": "Mini-série",
    "Plateforme": "Canal+",
    "Pays": "US",
    "Note": null
  },
  {
    "Date": "18/01/2024",
    "Heure": "21:00:00",
    "Titre": "Fargo",
    "Saison": "Saison 5",
    "Plateforme": "Canal+",
    "Pays": "US",
    "Note": null
  },
  {
    "Date": "18/01/2024",
    "Heure": "21:00:00",
    "Titre": "Angelyne",
    "Saison": "Mini-série",
    "Plateforme": "OCS Max",
    "Pays": "US",
    "Note": null
  },
  {
    "Date": "19/01/2024",
    "Heure": "00:00:00",
    "Titre": "Ancestral",
    "Saison": "Saison 1",
    "Plateforme": "Netflix",
    "Pays": "CDS",
    "Note": null
  },
  {
    "Date": "19/01/2024",
    "Heure": "21:25:00",
    "Titre": "Benoît Gênant officiel",
    "Saison": "Saison 1",
    "Plateforme": "TMC",
    "Pays": "FRA",
    "Note": null
  },
  {
    "Date": "19/01/2024",
    "Heure": "00:00:00",
    "Titre": "Furia",
    "Saison": "Saison 2",
    "Plateforme": "Série Club",
    "Pays": "ALL, NOR",
    "Note": "Sur Série Club à la demande"
  },
  {
    "Date": "19/01/2024",
    "Heure": "00:00:00",
    "Titre": "Hazbin Hotel",
    "Saison": "Saison 1",
    "Plateforme": "Prime Video",
    "Pays": "US",
    "Note": null
  },
  {
    "Date": "19/01/2024",
    "Heure": "00:00:00",
    "Titre": "Cristobal Balenciaga",
    "Saison": "Saison 1",
    "Plateforme": "Disney+",
    "Pays": "ESP",
    "Note": null
  },
  {
    "Date": "20/01/2024",
    "Heure": "00:00:00",
    "Titre": "Captivating The King",
    "Saison": "Saison 1",
    "Plateforme": "Netflix",
    "Pays": "CDS",
    "Note": null
  },
  {
    "Date": "20/01/2024",
    "Heure": "00:00:00",
    "Titre": "The Woman in The Wall",
    "Saison": "Mini-série",
    "Plateforme": "Paramount+",
    "Pays": "UK",
    "Note": null
  },
  {
    "Date": "20/01/2024",
    "Heure": "21:00:00",
    "Titre": "Cleaning Lady",
    "Saison": "Saison 2",
    "Plateforme": "Série Club",
    "Pays": "US",
    "Note": null
  },
  {
    "Date": "22/01/2024",
    "Heure": "21:10:00",
    "Titre": "Coeurs noirs",
    "Saison": "Saison 1",
    "Plateforme": "France 2",
    "Pays": "FRA",
    "Note": "Disponible sur Prime Video"
  },
  {
    "Date": "22/01/2024",
    "Heure": "00:00:00",
    "Titre": "Narval ou presque",
    "Saison": "Saison 2",
    "Plateforme": "Netflix",
    "Pays": "US",
    "Note": null
  },
  {
    "Date": "22/01/2024",
    "Heure": "21:00:00",
    "Titre": "D’Argent et de sang",
    "Saison": "Partie 2",
    "Plateforme": "Canal+",
    "Pays": "FRA",
    "Note": null
  },
  {
    "Date": "22/01/2024",
    "Heure": "00:00:00",
    "Titre": "So Help Me Todd",
    "Saison": "Saison 1",
    "Plateforme": "Paramount+",
    "Pays": "US",
    "Note": null
  },
  {
    "Date": "22/01/2024",
    "Heure": "00:00:00",
    "Titre": "Dickie",
    "Saison": "Saison 2 partie 2",
    "Plateforme": "Adult Swim",
    "Pays": "BEL",
    "Note": null
  },
  {
    "Date": "23/01/2024",
    "Heure": "20:55:00",
    "Titre": "Dark Winds",
    "Saison": "Saison 2",
    "Plateforme": "Polar+",
    "Pays": "US",
    "Note": null
  },
  {
    "Date": "23/01/2024",
    "Heure": "20:55:00",
    "Titre": "Spencer Sisters : Detectives Agency",
    "Saison": "Saison 1",
    "Plateforme": "Warner TV",
    "Pays": "CAN",
    "Note": null
  },
  {
    "Date": "24/01/2024",
    "Heure": "00:00:00",
    "Titre": "American Dad!",
    "Saison": "Saison 19 partie 2",
    "Plateforme": "Disney+",
    "Pays": "US",
    "Note": null
  },
  {
    "Date": "25/01/2024",
    "Heure": "20:55:00",
    "Titre": "Après le verdict : les jurés mènent l’enquête",
    "Saison": "Mini-série",
    "Plateforme": "Arte",
    "Pays": "AUS",
    "Note": null
  },
  {
    "Date": "25/01/2024",
    "Heure": "00:00:00",
    "Titre": "Sexy Beast",
    "Saison": "Saison 1",
    "Plateforme": "Paramount+",
    "Pays": "UK",
    "Note": null
  },
  {
    "Date": "25/01/2024",
    "Heure": "00:00:00",
    "Titre": "Masters of The Universe: Revolution",
    "Saison": "Saison 1",
    "Plateforme": "Netflix",
    "Pays": "US",
    "Note": null
  },
  {
    "Date": "25/01/2024",
    "Heure": "00:00:00",
    "Titre": "Griselda",
    "Saison": "Mini-série",
    "Plateforme": "Netflix",
    "Pays": "US",
    "Note": null
  },
  {
    "Date": "26/01/2024",
    "Heure": "00:00:00",
    "Titre": "Masters of The Air",
    "Saison": "Mini-série",
    "Plateforme": "Apple TV+",
    "Pays": "US",
    "Note": null
  },
  {
    "Date": "26/01/2024",
    "Heure": "00:00:00",
    "Titre": "Expats",
    "Saison": "Mini-série",
    "Plateforme": "Prime Video",
    "Pays": "US",
    "Note": null
  },
  {
    "Date": "27/01/2024",
    "Heure": "00:00:00",
    "Titre": "Doctor Slump",
    "Saison": "Saison 1",
    "Plateforme": "Netflix",
    "Pays": "CDS",
    "Note": null
  },
  {
    "Date": "31/01/2024",
    "Heure": "00:00:00",
    "Titre": "Seven Deadly Sins : Four Knights of The Apocalypse",
    "Saison": "Saison 1",
    "Plateforme": "Netflix",
    "Pays": "JAP",
    "Note": null
  },
  {
    "Date": "31/01/2024",
    "Heure": "00:00:00",
    "Titre": "Baby Bandito",
    "Saison": "Mini-série",
    "Plateforme": "Netflix",
    "Pays": "CHI",
    "Note": null
  },
  {
    "Date": "31/01/2024",
    "Heure": "00:00:00",
    "Titre": "9-1-1",
    "Saison": "Saison 6",
    "Plateforme": "Disney+",
    "Pays": "US",
    "Note": null
  },
  {
    "Date": "02/02/2024",
    "Heure": "21:00:00",
    "Titre": "Code Quantum (2022)",
    "Saison": "Saison 2",
    "Plateforme": "Série Club",
    "Pays": "US",
    "Note": null
  },
  {
    "Date": "02/02/2024",
    "Heure": "00:00:00",
    "Titre": "Mr. & Mrs. Smith",
    "Saison": "Saison 1",
    "Plateforme": "Prime Video",
    "Pays": "US",
    "Note": null
  },
  {
    "Date": "05/02/2024",
    "Heure": "00:00:00",
    "Titre": "Larry et son nombril",
    "Saison": "Saison 12",
    "Plateforme": "Pass Warner",
    "Pays": "US",
    "Note": "Dernière saison"
  },
  {
    "Date": "08/02/2024",
    "Heure": "00:00:00",
    "Titre": "Halo",
    "Saison": "Saison 2",
    "Plateforme": "Paramount+",
    "Pays": "US",
    "Note": null
  },
  {
    "Date": "08/02/2024",
    "Heure": "00:00:00",
    "Titre": "One Day",
    "Saison": "Mini-série",
    "Plateforme": "Netflix",
    "Pays": "UK",
    "Note": null
  },
  {
    "Date": "14/02/2024",
    "Heure": "00:00:00",
    "Titre": "The New Look",
    "Saison": "Mini-série",
    "Plateforme": "Apple TV+",
    "Pays": "US",
    "Note": null
  },
  {
    "Date": "21/02/2024",
    "Heure": "00:00:00",
    "Titre": "Constellation",
    "Saison": "Saison 1",
    "Plateforme": "Apple TV+",
    "Pays": "FRA, UK, US",
    "Note": null
  },
  {
    "Date": "22/02/2024",
    "Heure": "00:00:00",
    "Titre": "Avatar, le dernier maître de l’air",
    "Saison": "Saison 1",
    "Plateforme": "Netflix",
    "Pays": "US",
    "Note": null
  },
  {
    "Date": "23/02/2024",
    "Heure": "00:00:00",
    "Titre": "The Second Best Hospital in The Galaxy",
    "Saison": "Saison 1",
    "Plateforme": "Prime Video",
    "Pays": "US",
    "Note": null
  },
  {
    "Date": "27/02/2024",
    "Heure": "20:55:00",
    "Titre": "Found : les oubliés",
    "Saison": "Saison 1",
    "Plateforme": "Warner TV",
    "Pays": "US",
    "Note": "Déjà disponible sur le Pass Warner"
  },
  {
    "Date": "04/03/2024",
    "Heure": "00:00:00",
    "Titre": "The Regime",
    "Saison": "Mini-série",
    "Plateforme": "Pass Warner",
    "Pays": "US",
    "Note": null
  },
  {
    "Date": "06/03/2024",
    "Heure": "00:00:00",
    "Titre": "Supersex",
    "Saison": "Mini-série",
    "Plateforme": "Netflix",
    "Pays": "ITA",
    "Note": null
  },
  {
    "Date": "14/03/2024",
    "Heure": "00:00:00",
    "Titre": "Girls5eva",
    "Saison": "Saison 3",
    "Plateforme": "Netflix",
    "Pays": "US",
    "Note": null
  },
  {
    "Date": "15/03/2024",
    "Heure": "00:00:00",
    "Titre": "Manhunt",
    "Saison": "Mini-série",
    "Plateforme": "Apple TV+",
    "Pays": "US",
    "Note": null
  },
  {
    "Date": "20/03/2024",
    "Heure": "00:00:00",
    "Titre": "Palm Royale",
    "Saison": "Mini-série",
    "Plateforme": "Apple TV+",
    "Pays": "US",
    "Note": null
  },
  {
    "Date": "21/03/2024",
    "Heure": "00:00:00",
    "Titre": "Le Problème à 3 corps",
    "Saison": "Saison 1",
    "Plateforme": "Netflix",
    "Pays": "US",
    "Note": "Titre original : “3 Body Problem”"
  },
  {
    "Date": "12/04/2024",
    "Heure": "00:00:00",
    "Titre": "Fallout",
    "Saison": "Saison 1",
    "Plateforme": "Prime Video",
    "Pays": "US",
    "Note": null
  },
  {
    "Date": "16/05/2024",
    "Heure": "00:00:00",
    "Titre": "La Chronique des Bridgerton",
    "Saison": "Saison 3 partie 1",
    "Plateforme": "Netflix",
    "Pays": "US",
    "Note": null
  },
  {
    "Date": "13/06/2024",
    "Heure": "00:00:00",
    "Titre": "La Chronique des Bridgerton",
    "Saison": "Saison 3 partie 2",
    "Plateforme": "Netflix",
    "Pays": "US",
    "Note": null
  }
]